{
  "trial_idx": 168,
  "ITI1": {
    "phase_start": 567226.6295428,
    "eye_pos": [
      {
        "eyeX": 903,
        "eyeY": 341.79998779296875,
        "pupSize": 2145
      },
      {
        "eyeX": 902.29998779296875,
        "eyeY": 349.60000610351562,
        "pupSize": 2124
      },
      {
        "eyeX": 902.79998779296875,
        "eyeY": 355,
        "pupSize": 2113
      },
      {
        "eyeX": 901.79998779296875,
        "eyeY": 350.29998779296875,
        "pupSize": 2131
      },
      {
        "eyeX": 900.29998779296875,
        "eyeY": 347.39999389648438,
        "pupSize": 2139
      },
      {
        "eyeX": 900.4000244140625,
        "eyeY": 347.70001220703125,
        "pupSize": 2138
      },
      {
        "eyeX": 901.0999755859375,
        "eyeY": 348,
        "pupSize": 2138
      },
      {
        "eyeX": 900.9000244140625,
        "eyeY": 346.20001220703125,
        "pupSize": 2148
      },
      {
        "eyeX": 899.9000244140625,
        "eyeY": 346.60000610351562,
        "pupSize": 2144
      },
      {
        "eyeX": 899.20001220703125,
        "eyeY": 348.70001220703125,
        "pupSize": 2145
      },
      {
        "eyeX": 900,
        "eyeY": 349.20001220703125,
        "pupSize": 2141
      },
      {
        "eyeX": 900.4000244140625,
        "eyeY": 350,
        "pupSize": 2144
      },
      {
        "eyeX": 900,
        "eyeY": 347.60000610351562,
        "pupSize": 2155
      },
      {
        "eyeX": 900.79998779296875,
        "eyeY": 347.20001220703125,
        "pupSize": 2156
      },
      {
        "eyeX": 900.70001220703125,
        "eyeY": 346.5,
        "pupSize": 2154
      },
      {
        "eyeX": 901.79998779296875,
        "eyeY": 346.60000610351562,
        "pupSize": 2160
      },
      {
        "eyeX": 901.0999755859375,
        "eyeY": 346,
        "pupSize": 2161
      },
      {
        "eyeX": 901.29998779296875,
        "eyeY": 344.20001220703125,
        "pupSize": 2171
      },
      {
        "eyeX": 901.5999755859375,
        "eyeY": 342.70001220703125,
        "pupSize": 2173
      },
      {
        "eyeX": 901.70001220703125,
        "eyeY": 341.20001220703125,
        "pupSize": 2177
      },
      {
        "eyeX": 902.9000244140625,
        "eyeY": 338.70001220703125,
        "pupSize": 2184
      },
      {
        "eyeX": 902.0999755859375,
        "eyeY": 339.60000610351562,
        "pupSize": 2187
      },
      {
        "eyeX": 902.29998779296875,
        "eyeY": 340,
        "pupSize": 2192
      },
      {
        "eyeX": 901.20001220703125,
        "eyeY": 341.29998779296875,
        "pupSize": 2187
      },
      {
        "eyeX": 902.29998779296875,
        "eyeY": 342.70001220703125,
        "pupSize": 2199
      },
      {
        "eyeX": 901.5999755859375,
        "eyeY": 340.89999389648438,
        "pupSize": 2198
      },
      {
        "eyeX": 900.9000244140625,
        "eyeY": 339.5,
        "pupSize": 2200
      },
      {
        "eyeX": 901.20001220703125,
        "eyeY": 338.89999389648438,
        "pupSize": 2199
      },
      {
        "eyeX": 901.4000244140625,
        "eyeY": 338.39999389648438,
        "pupSize": 2197
      },
      {
        "eyeX": 900.79998779296875,
        "eyeY": 339.29998779296875,
        "pupSize": 2198
      },
      {
        "eyeX": 902.20001220703125,
        "eyeY": 337.89999389648438,
        "pupSize": 2203
      },
      {
        "eyeX": 902.4000244140625,
        "eyeY": 337.5,
        "pupSize": 2212
      }
    ],
    "all_joy_vec": -1,
    "phase_end": 567227.1446617,
    "phase_duration": 0.51511889998801053
  },
  "eels": [
    {
      "eel_col": [
        0,
        0,
        255
      ],
      "reliability": 0.1,
      "competency": 0.75,
      "initial_side": 2,
      "final_side": 2,
      "eel_pos": [
        1448,
        491
      ],
      "fish_pos": [
        [
          1570.4113392355891,
          610.87949591111283
        ],
        [
          1630.9375379058456,
          615.224188450717
        ],
        [
          1446.6246048637297,
          670.12701261496272
        ],
        [
          1451.9471967902725,
          714.02230023309187
        ],
        [
          1281.2710212660024,
          634.4883898931231
        ],
        [
          1262.2443661847203,
          626.51294165372485
        ],
        [
          1274.8012383317161,
          469.0007863879664
        ],
        [
          1258.1841120732086,
          367.02271157634084
        ]
      ]
    },
    {
      "eel_col": [
        157,
        0,
        255
      ],
      "reliability": 0.25,
      "competency": 0.27831576837137406,
      "initial_side": 1,
      "final_side": 1,
      "eel_pos": [
        526,
        562
      ],
      "fish_pos": [
        [
          657.65206978306355,
          694.26786735825112
        ],
        [
          705.42360500978782,
          692.82117321384658
        ],
        [
          506.00170022601736,
          750.10736360483384
        ],
        [
          597.01560300559925,
          736.55463184848043
        ],
        [
          375.35588693482953,
          646.09155662384137
        ],
        [
          331.83429163779715,
          661.93835083807
        ],
        [
          351.4429914125223,
          481.475122846329
        ],
        [
          335.64771292374041,
          523.68626093069486
        ]
      ]
    }
  ],
  "avtr_start_pos": [
    960,
    540
  ],
  "REPORT": {
    "choice": 1,
    "choice_side": "right",
    "reported_competency": 1,
    "reported_reliability": 1,
    "reporting_on_left": false,
    "corner_assignments": [
      4,
      3,
      2,
      1
    ],
    "random_rotation": 156.97623644727429,
    "state_positions": [
      [
        775.93145646497737,
        618.22257526376575
      ],
      [
        881.77742473623425,
        355.93145646497737
      ],
      [
        1144.0685435350226,
        461.77742473623425
      ],
      [
        1038.2225752637657,
        724.06854353502263
      ]
    ],
    "target_eel_idx": 1,
    "target_eel_color": [
      0,
      0,
      255
    ],
    "target_eel_side": 2,
    "target_eel_reliability": 0.1,
    "target_eel_competency": 0.75,
    "phase_start": 567227.1447585,
    "phase_end": 567228.0069623,
    "phase_duration": 0.86220380000304431,
    "choice_time": 567227.9926555,
    "choice_position": [
      1006.0551322330286,
      651.74803858433813
    ],
    "all_avatar_pos": [],
    "all_eye_data": [],
    "all_joy_vec": [
      [
        0,
        0
      ],
      [
        0,
        0
      ],
      [
        0,
        0
      ],
      [
        0,
        0
      ],
      [
        0,
        0
      ],
      [
        0,
        0
      ],
      [
        0,
        0
      ],
      [
        0,
        0
      ],
      [
        0,
        0
      ],
      [
        0,
        0
      ],
      [
        0,
        0
      ],
      [
        0,
        0
      ],
      [
        0,
        0
      ],
      [
        0,
        0
      ],
      [
        0,
        0
      ],
      [
        0,
        0
      ],
      [
        0,
        0
      ],
      [
        0,
        0
      ],
      [
        0,
        0
      ],
      [
        0,
        0
      ],
      [
        0,
        0
      ],
      [
        0,
        0
      ],
      [
        0,
        0
      ],
      [
        0,
        0
      ],
      [
        0,
        0
      ],
      [
        0,
        0
      ],
      [
        0,
        0
      ],
      [
        0,
        0
      ],
      [
        0,
        0
      ],
      [
        0,
        0
      ],
      [
        0,
        0
      ],
      [
        0,
        0
      ],
      [
        0,
        0
      ],
      [
        0,
        0
      ],
      [
        0,
        0
      ],
      [
        0,
        0
      ],
      [
        0,
        0
      ],
      [
        0.5061851264866909,
        0.86242484758015447
      ],
      [
        0.40870090054811731,
        0.9126683811172368
      ],
      [
        0.37432238360776404,
        0.92729863211923369
      ],
      [
        0.37495267753694228,
        0.92704395236033865
      ],
      [
        0.3714817820812073,
        0.92844024340921938
      ],
      [
        0.36793107789008739,
        0.92985306469497564
      ],
      [
        0.35422706260979503,
        0.93515944528985884
      ],
      [
        0.35725729806049517,
        0.93400600800129452
      ],
      [
        0.35725729806049517,
        0.93400600800129452
      ],
      [
        0.35725729806049517,
        0.93400600800129452
      ],
      [
        0.35725729806049517,
        0.93400600800129452
      ],
      [
        0.35725729806049517,
        0.93400600800129452
      ]
    ],
    "avtr_pos": [
      [
        960,
        540
      ],
      [
        960,
        540
      ],
      [
        960,
        540
      ],
      [
        960,
        540
      ],
      [
        960,
        540
      ],
      [
        960,
        540
      ],
      [
        960,
        540
      ],
      [
        960,
        540
      ],
      [
        960,
        540
      ],
      [
        960,
        540
      ],
      [
        960,
        540
      ],
      [
        960,
        540
      ],
      [
        960,
        540
      ],
      [
        960,
        540
      ],
      [
        960,
        540
      ],
      [
        960,
        540
      ],
      [
        960,
        540
      ],
      [
        960,
        540
      ],
      [
        960,
        540
      ],
      [
        960,
        540
      ],
      [
        960,
        540
      ],
      [
        960,
        540
      ],
      [
        960,
        540
      ],
      [
        960,
        540
      ],
      [
        960,
        540
      ],
      [
        960,
        540
      ],
      [
        960,
        540
      ],
      [
        960,
        540
      ],
      [
        960,
        540
      ],
      [
        960,
        540
      ],
      [
        960,
        540
      ],
      [
        960,
        540
      ],
      [
        960,
        540
      ],
      [
        960,
        540
      ],
      [
        960,
        540
      ],
      [
        960,
        540
      ],
      [
        960,
        540
      ],
      [
        965.56803639135364,
        549.48667332338175
      ],
      [
        970.063746297383,
        559.52602551567134
      ],
      [
        974.18129251706841,
        569.72631046898289
      ],
      [
        978.30577196997478,
        579.92379394494662
      ],
      [
        982.39207157286808,
        590.136636622448
      ],
      [
        986.439313429659,
        600.36502033409272
      ],
      [
        990.33581111836679,
        610.65177423228113
      ],
      [
        994.26564139703225,
        620.92584032029538
      ],
      [
        998.19547167569772,
        631.19990640830963
      ],
      [
        1002.1253019543632,
        641.47397249632388
      ],
      [
        1006.0551322330286,
        651.74803858433813
      ],
      [
        1009.9849625116941,
        662.02210467235238
      ]
    ],
    "eye_pos": [
      {
        "eyeX": 904.0999755859375,
        "eyeY": 338.29998779296875,
        "pupSize": 2209
      },
      {
        "eyeX": 905.5,
        "eyeY": 338.29998779296875,
        "pupSize": 2212
      },
      {
        "eyeX": 905.9000244140625,
        "eyeY": 338.29998779296875,
        "pupSize": 2207
      },
      {
        "eyeX": 907.70001220703125,
        "eyeY": 337.5,
        "pupSize": 2213
      },
      {
        "eyeX": 907.9000244140625,
        "eyeY": 337.60000610351562,
        "pupSize": 2213
      },
      {
        "eyeX": 909.70001220703125,
        "eyeY": 336.70001220703125,
        "pupSize": 2211
      },
      {
        "eyeX": 911.20001220703125,
        "eyeY": 337.60000610351562,
        "pupSize": 2211
      },
      {
        "eyeX": 911.29998779296875,
        "eyeY": 336.70001220703125,
        "pupSize": 2221
      },
      {
        "eyeX": 911.70001220703125,
        "eyeY": 337.39999389648438,
        "pupSize": 2218
      },
      {
        "eyeX": 913.29998779296875,
        "eyeY": 337.5,
        "pupSize": 2218
      },
      {
        "eyeX": 914.0999755859375,
        "eyeY": 336.89999389648438,
        "pupSize": 2225
      },
      {
        "eyeX": 914.5999755859375,
        "eyeY": 337.39999389648438,
        "pupSize": 2227
      },
      {
        "eyeX": 915.20001220703125,
        "eyeY": 337.60000610351562,
        "pupSize": 2236
      },
      {
        "eyeX": 917,
        "eyeY": 338.60000610351562,
        "pupSize": 2234
      },
      {
        "eyeX": 917.0999755859375,
        "eyeY": 337.29998779296875,
        "pupSize": 2237
      },
      {
        "eyeX": 922.0999755859375,
        "eyeY": 338.5,
        "pupSize": 2236
      },
      {
        "eyeX": 1051.5999755859375,
        "eyeY": 388,
        "pupSize": 2262
      },
      {
        "eyeX": 1121.300048828125,
        "eyeY": 426.39999389648438,
        "pupSize": 2236
      },
      {
        "eyeX": 1115.699951171875,
        "eyeY": 428.70001220703125,
        "pupSize": 2245
      },
      {
        "eyeX": 1115.5,
        "eyeY": 430.10000610351562,
        "pupSize": 2249
      },
      {
        "eyeX": 1115.0999755859375,
        "eyeY": 430.20001220703125,
        "pupSize": 2249
      },
      {
        "eyeX": 1114.9000244140625,
        "eyeY": 429.5,
        "pupSize": 2257
      },
      {
        "eyeX": 1114.9000244140625,
        "eyeY": 429.29998779296875,
        "pupSize": 2254
      },
      {
        "eyeX": 1115.0999755859375,
        "eyeY": 431.20001220703125,
        "pupSize": 2252
      },
      {
        "eyeX": 1114.800048828125,
        "eyeY": 430.29998779296875,
        "pupSize": 2250
      },
      {
        "eyeX": 1114.5,
        "eyeY": 429.10000610351562,
        "pupSize": 2255
      },
      {
        "eyeX": 1114.0999755859375,
        "eyeY": 428.5,
        "pupSize": 2254
      },
      {
        "eyeX": 1106,
        "eyeY": 448,
        "pupSize": 2264
      },
      {
        "eyeX": 1056.800048828125,
        "eyeY": 519.5999755859375,
        "pupSize": 2334
      },
      {
        "eyeX": 1022,
        "eyeY": 617.70001220703125,
        "pupSize": 2354
      },
      {
        "eyeX": 1021.7000122070312,
        "eyeY": 619.20001220703125,
        "pupSize": 2350
      },
      {
        "eyeX": 1023.2000122070312,
        "eyeY": 618.79998779296875,
        "pupSize": 2356
      },
      {
        "eyeX": 1022.9000244140625,
        "eyeY": 617.79998779296875,
        "pupSize": 2359
      },
      {
        "eyeX": 1022.9000244140625,
        "eyeY": 619.9000244140625,
        "pupSize": 2354
      },
      {
        "eyeX": 1023.4000244140625,
        "eyeY": 617.5,
        "pupSize": 2357
      },
      {
        "eyeX": 1023.2999877929688,
        "eyeY": 618.9000244140625,
        "pupSize": 2366
      },
      {
        "eyeX": 1023.7999877929688,
        "eyeY": 617.9000244140625,
        "pupSize": 2362
      },
      {
        "eyeX": 1024.699951171875,
        "eyeY": 619.29998779296875,
        "pupSize": 2366
      },
      {
        "eyeX": 1025,
        "eyeY": 619.9000244140625,
        "pupSize": 2366
      },
      {
        "eyeX": 1026.5,
        "eyeY": 621.4000244140625,
        "pupSize": 2365
      },
      {
        "eyeX": 1026.5,
        "eyeY": 620.5999755859375,
        "pupSize": 2364
      },
      {
        "eyeX": 1028,
        "eyeY": 620,
        "pupSize": 2372
      },
      {
        "eyeX": 1027.300048828125,
        "eyeY": 621.20001220703125,
        "pupSize": 2370
      },
      {
        "eyeX": 1027,
        "eyeY": 620.9000244140625,
        "pupSize": 2369
      },
      {
        "eyeX": 1027.5999755859375,
        "eyeY": 622.4000244140625,
        "pupSize": 2374
      },
      {
        "eyeX": 1026.5999755859375,
        "eyeY": 623,
        "pupSize": 2366
      },
      {
        "eyeX": 1026.5999755859375,
        "eyeY": 622.5999755859375,
        "pupSize": 2376
      },
      {
        "eyeX": 1028.300048828125,
        "eyeY": 624.4000244140625,
        "pupSize": 2365
      },
      {
        "eyeX": 1029.4000244140625,
        "eyeY": 626.0999755859375,
        "pupSize": 2362
      }
    ]
  },
  "ITI2": {
    "phase_start": 567228.0070123,
    "eye_pos": [
      {
        "eyeX": 1030.300048828125,
        "eyeY": 626.79998779296875,
        "pupSize": 2358
      },
      {
        "eyeX": 1031.0999755859375,
        "eyeY": 628.79998779296875,
        "pupSize": 2353
      },
      {
        "eyeX": 1032.699951171875,
        "eyeY": 627.5,
        "pupSize": 2347
      },
      {
        "eyeX": 1032.699951171875,
        "eyeY": 629.4000244140625,
        "pupSize": 2334
      },
      {
        "eyeX": 1033.5999755859375,
        "eyeY": 632.29998779296875,
        "pupSize": 2329
      },
      {
        "eyeX": 1032.800048828125,
        "eyeY": 625.9000244140625,
        "pupSize": 2370
      },
      {
        "eyeX": 1037.5999755859375,
        "eyeY": 633.5,
        "pupSize": 2295
      },
      {
        "eyeX": 1090,
        "eyeY": 899.79998779296875,
        "pupSize": 1520
      },
      {
        "eyeX": 1050.699951171875,
        "eyeY": 1131.699951171875,
        "pupSize": 691
      },
      {
        "eyeX": 1587.5999755859375,
        "eyeY": 1285.9000244140625,
        "pupSize": 151
      },
      {
        "eyeX": -32768,
        "eyeY": -32768,
        "pupSize": 0
      },
      {
        "eyeX": -32768,
        "eyeY": -32768,
        "pupSize": 0
      },
      {
        "eyeX": 1542.699951171875,
        "eyeY": 1011.2000122070312,
        "pupSize": 230
      },
      {
        "eyeX": 1049.5999755859375,
        "eyeY": 834.79998779296875,
        "pupSize": 893
      },
      {
        "eyeX": 1036,
        "eyeY": 635.79998779296875,
        "pupSize": 1734
      },
      {
        "eyeX": 997.0999755859375,
        "eyeY": 468.29998779296875,
        "pupSize": 2166
      },
      {
        "eyeX": 975.79998779296875,
        "eyeY": 389.20001220703125,
        "pupSize": 2440
      },
      {
        "eyeX": 969.0999755859375,
        "eyeY": 425.79998779296875,
        "pupSize": 2331
      },
      {
        "eyeX": 968.70001220703125,
        "eyeY": 431.89999389648438,
        "pupSize": 2329
      },
      {
        "eyeX": 968.5999755859375,
        "eyeY": 436.10000610351562,
        "pupSize": 2318
      },
      {
        "eyeX": 967.4000244140625,
        "eyeY": 445.5,
        "pupSize": 2296
      },
      {
        "eyeX": 967.20001220703125,
        "eyeY": 445,
        "pupSize": 2294
      },
      {
        "eyeX": 967.79998779296875,
        "eyeY": 442.5,
        "pupSize": 2293
      },
      {
        "eyeX": 967.5999755859375,
        "eyeY": 441.20001220703125,
        "pupSize": 2297
      },
      {
        "eyeX": 967.4000244140625,
        "eyeY": 438.70001220703125,
        "pupSize": 2296
      },
      {
        "eyeX": 968,
        "eyeY": 439.20001220703125,
        "pupSize": 2298
      },
      {
        "eyeX": 967.29998779296875,
        "eyeY": 437.89999389648438,
        "pupSize": 2296
      },
      {
        "eyeX": 966,
        "eyeY": 438.10000610351562,
        "pupSize": 2294
      },
      {
        "eyeX": 966,
        "eyeY": 436.70001220703125,
        "pupSize": 2297
      },
      {
        "eyeX": 966,
        "eyeY": 437.10000610351562,
        "pupSize": 2298
      },
      {
        "eyeX": 965.9000244140625,
        "eyeY": 435.5,
        "pupSize": 2295
      },
      {
        "eyeX": 965.5999755859375,
        "eyeY": 433,
        "pupSize": 2307
      }
    ],
    "all_joy_vec": -1,
    "phase_end": 567228.5079809,
    "phase_duration": 0.500968600041233
  },
  "CHOICE": {
    "choice": 2,
    "phase_start": 567228.5080322,
    "choice_side": "right",
    "avtr_pos": [
      [
        960,
        446.87444843483854
      ],
      [
        960,
        446.87444843483854
      ],
      [
        960,
        446.87444843483854
      ],
      [
        960,
        446.87444843483854
      ],
      [
        960,
        446.87444843483854
      ],
      [
        960,
        446.87444843483854
      ],
      [
        960,
        446.87444843483854
      ],
      [
        960,
        446.87444843483854
      ],
      [
        960,
        446.87444843483854
      ],
      [
        960,
        446.87444843483854
      ],
      [
        960,
        446.87444843483854
      ],
      [
        960,
        446.87444843483854
      ],
      [
        960,
        446.87444843483854
      ],
      [
        960,
        446.87444843483854
      ],
      [
        960,
        446.87444843483854
      ],
      [
        960,
        446.87444843483854
      ],
      [
        960,
        446.87444843483854
      ],
      [
        960,
        446.87444843483854
      ],
      [
        960,
        446.87444843483854
      ],
      [
        960,
        446.87444843483854
      ],
      [
        960,
        446.87444843483854
      ],
      [
        960,
        446.87444843483854
      ],
      [
        960,
        446.87444843483854
      ],
      [
        960,
        446.87444843483854
      ],
      [
        960,
        446.87444843483854
      ],
      [
        960,
        446.87444843483854
      ],
      [
        960,
        446.87444843483854
      ],
      [
        960,
        446.87444843483854
      ],
      [
        960,
        446.87444843483854
      ],
      [
        960,
        446.87444843483854
      ],
      [
        960,
        446.87444843483854
      ],
      [
        960,
        446.87444843483854
      ],
      [
        960,
        446.87444843483854
      ],
      [
        960,
        446.87444843483854
      ],
      [
        960,
        446.87444843483854
      ],
      [
        970.54342566218884,
        443.73818069979149
      ],
      [
        980.71254095308814,
        439.54424529251605
      ],
      [
        990.7311840994804,
        435.0025727475998
      ],
      [
        1000.7388881102706,
        430.43684603299965
      ],
      [
        1010.7554090139789,
        425.89049486029256
      ]
    ],
    "eye_pos": [
      {
        "eyeX": 963.79998779296875,
        "eyeY": 432,
        "pupSize": [],
        "pupilSize": 2304
      },
      {
        "eyeX": 963.5,
        "eyeY": 430.89999389648438,
        "pupSize": [],
        "pupilSize": 2301
      },
      {
        "eyeX": 964.29998779296875,
        "eyeY": 431.20001220703125,
        "pupSize": [],
        "pupilSize": 2299
      },
      {
        "eyeX": 963.9000244140625,
        "eyeY": 428.60000610351562,
        "pupSize": [],
        "pupilSize": 2303
      },
      {
        "eyeX": 964.29998779296875,
        "eyeY": 428.70001220703125,
        "pupSize": [],
        "pupilSize": 2297
      },
      {
        "eyeX": 963.4000244140625,
        "eyeY": 427.10000610351562,
        "pupSize": [],
        "pupilSize": 2294
      },
      {
        "eyeX": 963.5,
        "eyeY": 427.10000610351562,
        "pupSize": [],
        "pupilSize": 2291
      },
      {
        "eyeX": 963.20001220703125,
        "eyeY": 425.79998779296875,
        "pupSize": [],
        "pupilSize": 2284
      },
      {
        "eyeX": 963.29998779296875,
        "eyeY": 427,
        "pupSize": [],
        "pupilSize": 2275
      },
      {
        "eyeX": 961.5,
        "eyeY": 426.10000610351562,
        "pupSize": [],
        "pupilSize": 2267
      },
      {
        "eyeX": 960.29998779296875,
        "eyeY": 425.29998779296875,
        "pupSize": [],
        "pupilSize": 2263
      },
      {
        "eyeX": 959.5,
        "eyeY": 425,
        "pupSize": [],
        "pupilSize": 2252
      },
      {
        "eyeX": 959.5,
        "eyeY": 424.79998779296875,
        "pupSize": [],
        "pupilSize": 2238
      },
      {
        "eyeX": 958.70001220703125,
        "eyeY": 423.20001220703125,
        "pupSize": [],
        "pupilSize": 2229
      },
      {
        "eyeX": 958.5999755859375,
        "eyeY": 422.39999389648438,
        "pupSize": [],
        "pupilSize": 2219
      },
      {
        "eyeX": 958.0999755859375,
        "eyeY": 424,
        "pupSize": [],
        "pupilSize": 2206
      },
      {
        "eyeX": 957.9000244140625,
        "eyeY": 423.20001220703125,
        "pupSize": [],
        "pupilSize": 2201
      },
      {
        "eyeX": 957.70001220703125,
        "eyeY": 426.20001220703125,
        "pupSize": [],
        "pupilSize": 2187
      },
      {
        "eyeX": 957.5999755859375,
        "eyeY": 426.5,
        "pupSize": [],
        "pupilSize": 2182
      },
      {
        "eyeX": 1248,
        "eyeY": 408.5,
        "pupSize": [],
        "pupilSize": 2065
      },
      {
        "eyeX": 1372.699951171875,
        "eyeY": 400.29998779296875,
        "pupSize": [],
        "pupilSize": 1988
      },
      {
        "eyeX": 1371.0999755859375,
        "eyeY": 398.5,
        "pupSize": [],
        "pupilSize": 1991
      },
      {
        "eyeX": 1370.4000244140625,
        "eyeY": 397.79998779296875,
        "pupSize": [],
        "pupilSize": 1996
      },
      {
        "eyeX": 1372.300048828125,
        "eyeY": 398.20001220703125,
        "pupSize": [],
        "pupilSize": 1987
      },
      {
        "eyeX": 1372.5999755859375,
        "eyeY": 398.60000610351562,
        "pupSize": [],
        "pupilSize": 1979
      },
      {
        "eyeX": 1372,
        "eyeY": 399.10000610351562,
        "pupSize": [],
        "pupilSize": 1979
      },
      {
        "eyeX": 1372.0999755859375,
        "eyeY": 398.5,
        "pupSize": [],
        "pupilSize": 1969
      },
      {
        "eyeX": 1371.300048828125,
        "eyeY": 398.70001220703125,
        "pupSize": [],
        "pupilSize": 1974
      },
      {
        "eyeX": 1371.0999755859375,
        "eyeY": 399.60000610351562,
        "pupSize": [],
        "pupilSize": 1967
      },
      {
        "eyeX": 1326.800048828125,
        "eyeY": 361.39999389648438,
        "pupSize": [],
        "pupilSize": 1967
      },
      {
        "eyeX": 1297.0999755859375,
        "eyeY": 337.29998779296875,
        "pupSize": [],
        "pupilSize": 1952
      },
      {
        "eyeX": 1301.800048828125,
        "eyeY": 315.20001220703125,
        "pupSize": [],
        "pupilSize": 1932
      },
      {
        "eyeX": 1304.9000244140625,
        "eyeY": 313.89999389648438,
        "pupSize": [],
        "pupilSize": 1931
      },
      {
        "eyeX": 1305.5999755859375,
        "eyeY": 312.60000610351562,
        "pupSize": [],
        "pupilSize": 1924
      },
      {
        "eyeX": 1306.5,
        "eyeY": 314.10000610351562,
        "pupSize": [],
        "pupilSize": 1927
      },
      {
        "eyeX": 1306.5999755859375,
        "eyeY": 313.89999389648438,
        "pupSize": [],
        "pupilSize": 1921
      },
      {
        "eyeX": 1307.5,
        "eyeY": 313.5,
        "pupSize": [],
        "pupilSize": 1919
      },
      {
        "eyeX": 1307.9000244140625,
        "eyeY": 312.20001220703125,
        "pupSize": [],
        "pupilSize": 1928
      },
      {
        "eyeX": 1309.199951171875,
        "eyeY": 311.5,
        "pupSize": [],
        "pupilSize": 1925
      },
      {
        "eyeX": 1309.5,
        "eyeY": 312.79998779296875,
        "pupSize": [],
        "pupilSize": 1925
      }
    ],
    "all_joy_vec": [
      [
        0,
        0
      ],
      [
        0,
        0
      ],
      [
        0,
        0
      ],
      [
        0,
        0
      ],
      [
        0,
        0
      ],
      [
        0,
        0
      ],
      [
        0,
        0
      ],
      [
        0,
        0
      ],
      [
        0,
        0
      ],
      [
        0,
        0
      ],
      [
        0,
        0
      ],
      [
        0,
        0
      ],
      [
        0,
        0
      ],
      [
        0,
        0
      ],
      [
        0,
        0
      ],
      [
        0,
        0
      ],
      [
        0,
        0
      ],
      [
        0,
        0
      ],
      [
        0,
        0
      ],
      [
        0,
        0
      ],
      [
        0,
        0
      ],
      [
        0,
        0
      ],
      [
        0,
        0
      ],
      [
        0,
        0
      ],
      [
        0,
        0
      ],
      [
        0,
        0
      ],
      [
        0,
        0
      ],
      [
        0,
        0
      ],
      [
        0,
        0
      ],
      [
        0,
        0
      ],
      [
        0,
        0
      ],
      [
        0,
        0
      ],
      [
        0,
        0
      ],
      [
        0,
        0
      ],
      [
        0,
        0
      ],
      [
        0.95849324201717023,
        -0.28511524864064047
      ],
      [
        0.92446502644538919,
        -0.38126685520685655
      ],
      [
        0.91078574058111939,
        -0.41287932226511637
      ],
      [
        0.90979127370820145,
        -0.41506606496364951
      ],
      [
        0.9105928094280249,
        -0.41330465206428146
      ]
    ],
    "phase_end": 567229.201113,
    "phase_duration": 0.69308080000337213
  },
  "PURSUIT": {
    "phase_start": 567229.2011671,
    "side_switch_frames": [],
    "left_fish_caught": 0,
    "right_fish_caught": 3,
    "avtr_pos": [
      [
        1120.0539871736667,
        442.41156350334586
      ],
      [
        1130.1434291005799,
        438.02942229117025
      ],
      [
        1140.232871027493,
        433.64728107899464
      ],
      [
        1150.2914166426576,
        429.19467958013439
      ],
      [
        1160.3808585695708,
        424.81253836795878
      ],
      [
        1170.470300496484,
        420.43039715578317
      ],
      [
        1180.5597424233972,
        416.04825594360756
      ],
      [
        1190.6491843503104,
        411.66611473143195
      ],
      [
        1200.7386262772236,
        407.28397351925634
      ],
      [
        1210.8280682041368,
        402.90183230708072
      ],
      [
        1220.8580306642393,
        398.38521265861203
      ],
      [
        1230.9474725911525,
        394.00307144643642
      ],
      [
        1241.0060182063171,
        389.55046994757618
      ],
      [
        1251.0954601332303,
        385.16832873540056
      ],
      [
        1261.1849020601435,
        380.78618752322495
      ],
      [
        1271.2743439870567,
        376.40404631104934
      ],
      [
        1281.3984176071026,
        372.10251945005092
      ],
      [
        1291.5224912271485,
        367.8009925890525
      ],
      [
        1301.5890384060585,
        363.36651089501197
      ],
      [
        1311.7131120261045,
        359.06498403401355
      ],
      [
        1321.8371856461504,
        354.76345717301513
      ],
      [
        1331.9612592661963,
        350.4619303120167
      ],
      [
        1342.0853328862422,
        346.16040345101828
      ],
      [
        1352.2094065062881,
        341.85887659001986
      ],
      [
        1362.3334801263341,
        337.55734972902144
      ],
      [
        1372.45755374638,
        333.255822868023
      ],
      [
        1382.5816273664259,
        328.9542960070246
      ],
      [
        1392.7532252150745,
        324.76638516683653
      ],
      [
        1402.9248230637231,
        320.57847432664846
      ],
      [
        1413.0964209123717,
        316.39056348646039
      ],
      [
        1423.2680187610204,
        312.20265264627233
      ],
      [
        1433.3920923810663,
        307.9011257852739
      ],
      [
        1443.4586395599763,
        303.46664409123338
      ],
      [
        1453.6064466703419,
        299.221410192988
      ],
      [
        1463.7430199551154,
        294.94942212624255
      ],
      [
        1473.914617803764,
        290.76151128605449
      ],
      [
        1484.0862156524126,
        286.57360044586642
      ],
      [
        1494.2578135010613,
        282.38568960567835
      ],
      [
        1504.5378221287106,
        278.47143072110572
      ],
      [
        1515.1748368836531,
        275.66894662603323
      ],
      [
        1526.0430026953554,
        273.97101497565757
      ],
      [
        1537.0360752226461,
        273.58068638366211
      ],
      [
        1548.0354884564733,
        273.46707075309968
      ],
      [
        1559.0351010885838,
        273.55938512638403
      ],
      [
        1569.8648409277546,
        275.48726868507663
      ],
      [
        1580.2225674321323,
        279.19098326108121
      ],
      [
        1590.0544246203178,
        284.12399291352727
      ],
      [
        1599.4155010378806,
        289.90069165108935
      ],
      [
        1608.1175013049829,
        296.62937587249189
      ],
      [
        1616.3234803862731,
        303.95480468706836
      ],
      [
        1623.2798974830284,
        312.4758528136764
      ],
      [
        1629.5897882706547,
        321.48614017026108
      ],
      [
        1635.3253146266682,
        330.87249928439451
      ],
      [
        1640.5826738462224,
        340.53480615369693
      ]
    ],
    "eel_pos": {
      "left": [
        [
          null,
          null
        ],
        [
          null,
          null
        ],
        [
          null,
          null
        ],
        [
          null,
          null
        ],
        [
          null,
          null
        ],
        [
          null,
          null
        ],
        [
          null,
          null
        ],
        [
          null,
          null
        ],
        [
          null,
          null
        ],
        [
          null,
          null
        ],
        [
          null,
          null
        ],
        [
          null,
          null
        ],
        [
          null,
          null
        ],
        [
          null,
          null
        ],
        [
          null,
          null
        ],
        [
          null,
          null
        ],
        [
          null,
          null
        ],
        [
          null,
          null
        ],
        [
          null,
          null
        ],
        [
          null,
          null
        ],
        [
          null,
          null
        ],
        [
          null,
          null
        ],
        [
          null,
          null
        ],
        [
          null,
          null
        ],
        [
          null,
          null
        ],
        [
          null,
          null
        ],
        [
          null,
          null
        ],
        [
          null,
          null
        ],
        [
          null,
          null
        ],
        [
          null,
          null
        ],
        [
          null,
          null
        ],
        [
          null,
          null
        ],
        [
          null,
          null
        ],
        [
          null,
          null
        ],
        [
          null,
          null
        ],
        [
          null,
          null
        ],
        [
          null,
          null
        ],
        [
          null,
          null
        ],
        [
          null,
          null
        ],
        [
          null,
          null
        ],
        [
          null,
          null
        ],
        [
          null,
          null
        ],
        [
          null,
          null
        ],
        [
          null,
          null
        ],
        [
          null,
          null
        ],
        [
          null,
          null
        ],
        [
          null,
          null
        ],
        [
          null,
          null
        ],
        [
          null,
          null
        ],
        [
          null,
          null
        ],
        [
          null,
          null
        ],
        [
          null,
          null
        ],
        [
          null,
          null
        ],
        [
          null,
          null
        ]
      ],
      "right": [
        [
          1447.1901199965537,
          490.41340441527603
        ],
        [
          1446.4564204617673,
          489.73393035936658
        ],
        [
          1446.173155444438,
          488.77488868667587
        ],
        [
          1446.3817445112973,
          487.79688531184183
        ],
        [
          1446.8760304621005,
          486.92758593945132
        ],
        [
          1447.4509482187516,
          486.10937473622369
        ],
        [
          1448.1021415486982,
          485.35046285264764
        ],
        [
          1448.8200636111324,
          484.65433936340855
        ],
        [
          1449.569300867417,
          483.99203766946908
        ],
        [
          1450.3507403175911,
          483.36805659146142
        ],
        [
          1449.3538070338632,
          483.44631275924081
        ],
        [
          1448.3569406525185,
          483.52541660077128
        ],
        [
          1447.3604761206936,
          483.609431104371
        ],
        [
          1446.3642782319478,
          483.69655037008414
        ],
        [
          1445.3681932821612,
          483.78495157374476
        ],
        [
          1444.3723463427439,
          483.8759948230994
        ],
        [
          1443.3767414512097,
          483.96964790608683
        ],
        [
          1442.3813300493566,
          484.065335632891
        ],
        [
          1441.3862034730919,
          484.16394139951512
        ],
        [
          1440.3912852537605,
          484.26462772849061
        ],
        [
          1439.3967219611147,
          484.36876156987449
        ],
        [
          1438.402444714628,
          484.47559207637295
        ],
        [
          1437.4085691467637,
          484.58609707898574
        ],
        [
          1436.4144672946479,
          484.69454756363058
        ],
        [
          1435.419818823276,
          484.79786464061908
        ],
        [
          1434.4244993211571,
          484.89450360119685
        ],
        [
          1433.4287567387532,
          484.986681199275
        ],
        [
          1432.4325665718284,
          485.07388871799986
        ],
        [
          1431.4360213603743,
          485.15694075908243
        ],
        [
          1430.4389569258246,
          485.23350781045804
        ],
        [
          1429.4413105193739,
          485.3020763724686
        ],
        [
          1428.4549799506124,
          485.46685503955462
        ],
        [
          1427.4680843561407,
          485.62821515114427
        ],
        [
          1426.4806285319389,
          485.78611067118771
        ],
        [
          1425.4926928516359,
          485.94097542374391
        ],
        [
          1424.5042635874781,
          486.09265795324751
        ],
        [
          1423.5152183834678,
          486.24027090804532
        ],
        [
          1422.525617304324,
          486.38411006876771
        ],
        [
          1421.5353634622013,
          486.52338435986758
        ],
        [
          1420.5445198948669,
          486.65839926671873
        ],
        [
          1419.5530546448269,
          486.78877049806727
        ],
        [
          1418.5611888199724,
          486.91605830378876
        ],
        [
          1417.5688989233711,
          487.03999684139171
        ],
        [
          1416.5761772682336,
          487.16042821363681
        ],
        [
          1415.5830140461078,
          487.27716215992757
        ],
        [
          1414.5894507272938,
          487.39044027567468
        ],
        [
          1413.5954805634658,
          487.50009114625931
        ],
        [
          1412.6011280617349,
          487.60621891030678
        ],
        [
          1411.6063741845956,
          487.70851614348544
        ],
        [
          1410.6112510771527,
          487.80715691108827
        ],
        [
          1409.6157608931428,
          487.9020215174487
        ],
        [
          1408.6199117799445,
          487.99304098647696
        ],
        [
          1407.6237034599039,
          488.08004088924633
        ],
        [
          1406.6271399323082,
          488.16287286052415
        ]
      ]
    },
    "fish_pos": {
      "left": [
        [
          [
            null,
            null
          ],
          [
            null,
            null
          ],
          [
            null,
            null
          ],
          [
            null,
            null
          ],
          [
            null,
            null
          ],
          [
            null,
            null
          ]
        ],
        [
          [
            null,
            null
          ],
          [
            null,
            null
          ],
          [
            null,
            null
          ],
          [
            null,
            null
          ],
          [
            null,
            null
          ],
          [
            null,
            null
          ]
        ],
        [
          [
            null,
            null
          ],
          [
            null,
            null
          ],
          [
            null,
            null
          ],
          [
            null,
            null
          ],
          [
            null,
            null
          ],
          [
            null,
            null
          ]
        ],
        [
          [
            null,
            null
          ],
          [
            null,
            null
          ],
          [
            null,
            null
          ],
          [
            null,
            null
          ],
          [
            null,
            null
          ],
          [
            null,
            null
          ]
        ],
        [
          [
            null,
            null
          ],
          [
            null,
            null
          ],
          [
            null,
            null
          ],
          [
            null,
            null
          ],
          [
            null,
            null
          ],
          [
            null,
            null
          ]
        ],
        [
          [
            null,
            null
          ],
          [
            null,
            null
          ],
          [
            null,
            null
          ],
          [
            null,
            null
          ],
          [
            null,
            null
          ],
          [
            null,
            null
          ]
        ],
        [
          [
            null,
            null
          ],
          [
            null,
            null
          ],
          [
            null,
            null
          ],
          [
            null,
            null
          ],
          [
            null,
            null
          ],
          [
            null,
            null
          ]
        ],
        [
          [
            null,
            null
          ],
          [
            null,
            null
          ],
          [
            null,
            null
          ],
          [
            null,
            null
          ],
          [
            null,
            null
          ],
          [
            null,
            null
          ]
        ],
        [
          [
            null,
            null
          ],
          [
            null,
            null
          ],
          [
            null,
            null
          ],
          [
            null,
            null
          ],
          [
            null,
            null
          ],
          [
            null,
            null
          ]
        ],
        [
          [
            null,
            null
          ],
          [
            null,
            null
          ],
          [
            null,
            null
          ],
          [
            null,
            null
          ],
          [
            null,
            null
          ],
          [
            null,
            null
          ]
        ],
        [
          [
            null,
            null
          ],
          [
            null,
            null
          ],
          [
            null,
            null
          ],
          [
            null,
            null
          ],
          [
            null,
            null
          ],
          [
            null,
            null
          ]
        ],
        [
          [
            null,
            null
          ],
          [
            null,
            null
          ],
          [
            null,
            null
          ],
          [
            null,
            null
          ],
          [
            null,
            null
          ],
          [
            null,
            null
          ]
        ],
        [
          [
            null,
            null
          ],
          [
            null,
            null
          ],
          [
            null,
            null
          ],
          [
            null,
            null
          ],
          [
            null,
            null
          ],
          [
            null,
            null
          ]
        ],
        [
          [
            null,
            null
          ],
          [
            null,
            null
          ],
          [
            null,
            null
          ],
          [
            null,
            null
          ],
          [
            null,
            null
          ],
          [
            null,
            null
          ]
        ],
        [
          [
            null,
            null
          ],
          [
            null,
            null
          ],
          [
            null,
            null
          ],
          [
            null,
            null
          ],
          [
            null,
            null
          ],
          [
            null,
            null
          ]
        ],
        [
          [
            null,
            null
          ],
          [
            null,
            null
          ],
          [
            null,
            null
          ],
          [
            null,
            null
          ],
          [
            null,
            null
          ],
          [
            null,
            null
          ]
        ],
        [
          [
            null,
            null
          ],
          [
            null,
            null
          ],
          [
            null,
            null
          ],
          [
            null,
            null
          ],
          [
            null,
            null
          ],
          [
            null,
            null
          ]
        ],
        [
          [
            null,
            null
          ],
          [
            null,
            null
          ],
          [
            null,
            null
          ],
          [
            null,
            null
          ],
          [
            null,
            null
          ],
          [
            null,
            null
          ]
        ],
        [
          [
            null,
            null
          ],
          [
            null,
            null
          ],
          [
            null,
            null
          ],
          [
            null,
            null
          ],
          [
            null,
            null
          ],
          [
            null,
            null
          ]
        ],
        [
          [
            null,
            null
          ],
          [
            null,
            null
          ],
          [
            null,
            null
          ],
          [
            null,
            null
          ],
          [
            null,
            null
          ],
          [
            null,
            null
          ]
        ],
        [
          [
            null,
            null
          ],
          [
            null,
            null
          ],
          [
            null,
            null
          ],
          [
            null,
            null
          ],
          [
            null,
            null
          ],
          [
            null,
            null
          ]
        ],
        [
          [
            null,
            null
          ],
          [
            null,
            null
          ],
          [
            null,
            null
          ],
          [
            null,
            null
          ],
          [
            null,
            null
          ],
          [
            null,
            null
          ]
        ],
        [
          [
            null,
            null
          ],
          [
            null,
            null
          ],
          [
            null,
            null
          ],
          [
            null,
            null
          ],
          [
            null,
            null
          ],
          [
            null,
            null
          ]
        ],
        [
          [
            null,
            null
          ],
          [
            null,
            null
          ],
          [
            null,
            null
          ],
          [
            null,
            null
          ],
          [
            null,
            null
          ],
          [
            null,
            null
          ]
        ],
        [
          [
            null,
            null
          ],
          [
            null,
            null
          ],
          [
            null,
            null
          ],
          [
            null,
            null
          ],
          [
            null,
            null
          ],
          [
            null,
            null
          ]
        ],
        [
          [
            null,
            null
          ],
          [
            null,
            null
          ],
          [
            null,
            null
          ],
          [
            null,
            null
          ],
          [
            null,
            null
          ],
          [
            null,
            null
          ]
        ],
        [
          [
            null,
            null
          ],
          [
            null,
            null
          ],
          [
            null,
            null
          ],
          [
            null,
            null
          ],
          [
            null,
            null
          ],
          [
            null,
            null
          ]
        ],
        [
          [
            null,
            null
          ],
          [
            null,
            null
          ],
          [
            null,
            null
          ],
          [
            null,
            null
          ],
          [
            null,
            null
          ],
          [
            null,
            null
          ]
        ],
        [
          [
            null,
            null
          ],
          [
            null,
            null
          ],
          [
            null,
            null
          ],
          [
            null,
            null
          ],
          [
            null,
            null
          ],
          [
            null,
            null
          ]
        ],
        [
          [
            null,
            null
          ],
          [
            null,
            null
          ],
          [
            null,
            null
          ],
          [
            null,
            null
          ],
          [
            null,
            null
          ],
          [
            null,
            null
          ]
        ],
        [
          [
            null,
            null
          ],
          [
            null,
            null
          ],
          [
            null,
            null
          ],
          [
            null,
            null
          ],
          [
            null,
            null
          ],
          [
            null,
            null
          ]
        ],
        [
          [
            null,
            null
          ],
          [
            null,
            null
          ],
          [
            null,
            null
          ],
          [
            null,
            null
          ],
          [
            null,
            null
          ],
          [
            null,
            null
          ]
        ],
        [
          [
            null,
            null
          ],
          [
            null,
            null
          ],
          [
            null,
            null
          ],
          [
            null,
            null
          ],
          [
            null,
            null
          ],
          [
            null,
            null
          ]
        ],
        [
          [
            null,
            null
          ],
          [
            null,
            null
          ],
          [
            null,
            null
          ],
          [
            null,
            null
          ],
          [
            null,
            null
          ],
          [
            null,
            null
          ]
        ],
        [
          [
            null,
            null
          ],
          [
            null,
            null
          ],
          [
            null,
            null
          ],
          [
            null,
            null
          ],
          [
            null,
            null
          ],
          [
            null,
            null
          ]
        ],
        [
          [
            null,
            null
          ],
          [
            null,
            null
          ],
          [
            null,
            null
          ],
          [
            null,
            null
          ],
          [
            null,
            null
          ],
          [
            null,
            null
          ]
        ],
        [
          [
            null,
            null
          ],
          [
            null,
            null
          ],
          [
            null,
            null
          ],
          [
            null,
            null
          ],
          [
            null,
            null
          ],
          [
            null,
            null
          ]
        ],
        [
          [
            null,
            null
          ],
          [
            null,
            null
          ],
          [
            null,
            null
          ],
          [
            null,
            null
          ],
          [
            null,
            null
          ],
          [
            null,
            null
          ]
        ],
        [
          [
            null,
            null
          ],
          [
            null,
            null
          ],
          [
            null,
            null
          ],
          [
            null,
            null
          ],
          [
            null,
            null
          ],
          [
            null,
            null
          ]
        ],
        [
          [
            null,
            null
          ],
          [
            null,
            null
          ],
          [
            null,
            null
          ],
          [
            null,
            null
          ],
          [
            null,
            null
          ],
          [
            null,
            null
          ]
        ],
        [
          [
            null,
            null
          ],
          [
            null,
            null
          ],
          [
            null,
            null
          ],
          [
            null,
            null
          ],
          [
            null,
            null
          ],
          [
            null,
            null
          ]
        ],
        [
          [
            null,
            null
          ],
          [
            null,
            null
          ],
          [
            null,
            null
          ],
          [
            null,
            null
          ],
          [
            null,
            null
          ],
          [
            null,
            null
          ]
        ],
        [
          [
            null,
            null
          ],
          [
            null,
            null
          ],
          [
            null,
            null
          ],
          [
            null,
            null
          ],
          [
            null,
            null
          ],
          [
            null,
            null
          ]
        ],
        [
          [
            null,
            null
          ],
          [
            null,
            null
          ],
          [
            null,
            null
          ],
          [
            null,
            null
          ],
          [
            null,
            null
          ],
          [
            null,
            null
          ]
        ],
        [
          [
            null,
            null
          ],
          [
            null,
            null
          ],
          [
            null,
            null
          ],
          [
            null,
            null
          ],
          [
            null,
            null
          ],
          [
            null,
            null
          ]
        ],
        [
          [
            null,
            null
          ],
          [
            null,
            null
          ],
          [
            null,
            null
          ],
          [
            null,
            null
          ],
          [
            null,
            null
          ],
          [
            null,
            null
          ]
        ],
        [
          [
            null,
            null
          ],
          [
            null,
            null
          ],
          [
            null,
            null
          ],
          [
            null,
            null
          ],
          [
            null,
            null
          ],
          [
            null,
            null
          ]
        ],
        [
          [
            null,
            null
          ],
          [
            null,
            null
          ],
          [
            null,
            null
          ],
          [
            null,
            null
          ],
          [
            null,
            null
          ],
          [
            null,
            null
          ]
        ],
        [
          [
            null,
            null
          ],
          [
            null,
            null
          ],
          [
            null,
            null
          ],
          [
            null,
            null
          ],
          [
            null,
            null
          ],
          [
            null,
            null
          ]
        ],
        [
          [
            null,
            null
          ],
          [
            null,
            null
          ],
          [
            null,
            null
          ],
          [
            null,
            null
          ],
          [
            null,
            null
          ],
          [
            null,
            null
          ]
        ],
        [
          [
            null,
            null
          ],
          [
            null,
            null
          ],
          [
            null,
            null
          ],
          [
            null,
            null
          ],
          [
            null,
            null
          ],
          [
            null,
            null
          ]
        ],
        [
          [
            null,
            null
          ],
          [
            null,
            null
          ],
          [
            null,
            null
          ],
          [
            null,
            null
          ],
          [
            null,
            null
          ],
          [
            null,
            null
          ]
        ],
        [
          [
            null,
            null
          ],
          [
            null,
            null
          ],
          [
            null,
            null
          ],
          [
            null,
            null
          ],
          [
            null,
            null
          ],
          [
            null,
            null
          ]
        ],
        [
          [
            null,
            null
          ],
          [
            null,
            null
          ],
          [
            null,
            null
          ],
          [
            null,
            null
          ],
          [
            null,
            null
          ],
          [
            null,
            null
          ]
        ]
      ],
      "right": [
        [
          [
            1602.6917732380907,
            661.6675020992177
          ],
          [
            1504.4098434272571,
            718.57431186798749
          ],
          [
            1203.7550745332578,
            518.1262683522059
          ],
          [
            1203.2937432487429,
            391.17843265154636
          ],
          [
            1487.9711633368279,
            267.47183785414381
          ],
          [
            1656.2888743158721,
            335.92149040271477
          ]
        ],
        [
          [
            1604.2358142036694,
            661.91162601765154
          ],
          [
            1504.5499293642904,
            717.12023399467557
          ],
          [
            1205.9201289031025,
            518.29851082207676
          ],
          [
            1210.3026245743308,
            383.418340253452
          ],
          [
            1486.9241347772081,
            268.36808656802378
          ],
          [
            1660.2588606908009,
            331.878385202536
          ]
        ],
        [
          [
            1605.8511296211409,
            661.89468162369474
          ],
          [
            1504.6711583648641,
            715.20534071073541
          ],
          [
            1207.5347477294133,
            518.79999123152334
          ],
          [
            1218.3502811933613,
            376.75994749921296
          ],
          [
            1485.9454936054287,
            269.43082896174167
          ],
          [
            1665.7773508930659,
            326.52868757712793
          ]
        ],
        [
          [
            1607.2392681660713,
            661.79310800428277
          ],
          [
            1505.0180220324146,
            713.6881196214897
          ],
          [
            1209.455341013695,
            519.8659340196042
          ],
          [
            1226.8496061636631,
            371.22734340720717
          ],
          [
            1484.9280164707986,
            270.90067044180904
          ],
          [
            1669.7845816183753,
            321.11336575494806
          ]
        ],
        [
          [
            1608.6836278303265,
            661.860117329049
          ],
          [
            1505.5824747979611,
            712.27178629029311
          ],
          [
            1211.30564481349,
            521.16396116783278
          ],
          [
            1228.9639456269865,
            369.57384713041
          ],
          [
            1483.7655738283663,
            272.09691592352345
          ],
          [
            1672.7624597345307,
            316.36586480391486
          ]
        ],
        [
          [
            1610.1842733170583,
            662.16862929043407
          ],
          [
            1506.4576462192447,
            710.6631145081102
          ],
          [
            1213.0646434462535,
            522.50225397799011
          ],
          [
            1230.7743791604314,
            367.91192662551879
          ],
          [
            1482.3840119899376,
            273.4281602931955
          ],
          [
            1677.0371662265029,
            311.56258236681077
          ]
        ],
        [
          [
            1611.5262567882392,
            662.52164916299864
          ],
          [
            1507.5194905828052,
            709.18339019623011
          ],
          [
            1214.3453849991631,
            523.5811885169926
          ],
          [
            1232.9245431699385,
            366.19748947816691
          ],
          [
            1481.0098292284997,
            274.77533204421945
          ],
          [
            1681.9252050625591,
            307.61193518896408
          ]
        ],
        [
          [
            1613.1177291000351,
            662.66644772170514
          ],
          [
            1508.225289229686,
            707.742867461105
          ],
          [
            1215.4645665742703,
            525.12385939883643
          ],
          [
            1234.8488371037056,
            364.23290482576135
          ],
          [
            1479.6052449592191,
            275.7744998067044
          ],
          [
            1686.5632410779808,
            302.48093402513018
          ]
        ],
        [
          [
            1614.7667475955031,
            663.09089324654622
          ],
          [
            1508.7417675716581,
            706.43930245179888
          ],
          [
            1216.7409074815655,
            526.72829040535908
          ],
          [
            1236.7886741535958,
            362.28366594356311
          ],
          [
            1477.9889434618581,
            276.76979301789748
          ],
          [
            1692.0438354477471,
            297.27273597559616
          ]
        ],
        [
          [
            1616.1262355449967,
            663.6392119658
          ],
          [
            1509.1882010625595,
            705.12801741453916
          ],
          [
            1217.5277746265656,
            528.35259715946768
          ],
          [
            -1,
            -1
          ],
          [
            1476.5110994419117,
            277.89964223422737
          ],
          [
            1694.5057419910554,
            293.69897209458253
          ]
        ],
        [
          [
            1617.8949288492711,
            664.119433330375
          ],
          [
            1509.9811002382075,
            703.47978921961783
          ],
          [
            1217.971543230962,
            530.06481847402949
          ],
          [
            -1,
            -1
          ],
          [
            1474.9339137335403,
            278.83705974618022
          ],
          [
            1692.7500153367093,
            293.37018323360587
          ]
        ],
        [
          [
            1619.2232617021109,
            664.47484303952137
          ],
          [
            1510.8270411913447,
            701.75091590310535
          ],
          [
            1218.0981113775626,
            531.83269524609148
          ],
          [
            -1,
            -1
          ],
          [
            1473.4623150415721,
            279.40986808139911
          ],
          [
            1682.2908985337858,
            296.36994246341112
          ]
        ],
        [
          [
            1621.0609569371786,
            665.02861915526523
          ],
          [
            1511.3413191864659,
            700.445290605802
          ],
          [
            1217.9730641100753,
            533.747953984252
          ],
          [
            -1,
            -1
          ],
          [
            1472.2019685208274,
            280.00107741688066
          ],
          [
            1675.3464727852213,
            297.33082320464547
          ]
        ],
        [
          [
            1626.593553471768,
            666.16409823745073
          ],
          [
            1512.203041312973,
            699.00794602074461
          ],
          [
            1217.5966871656576,
            535.36419357214641
          ],
          [
            -1,
            -1
          ],
          [
            1470.9032396840428,
            280.50279339098358
          ],
          [
            1669.5600898484386,
            297.43196312996446
          ]
        ],
        [
          [
            1633.5949373758422,
            668.45149564296923
          ],
          [
            1513.2867712597076,
            697.7351403314799
          ],
          [
            1217.3462189713807,
            537.26966449312079
          ],
          [
            -1,
            -1
          ],
          [
            1469.4403165006177,
            280.82911500414752
          ],
          [
            1663.2120582551609,
            298.61829778043915
          ]
        ],
        [
          [
            1638.806660109019,
            670.21435719302076
          ],
          [
            1514.1732727577155,
            696.27375305237092
          ],
          [
            1217.3852219170635,
            538.89564267937624
          ],
          [
            -1,
            -1
          ],
          [
            1468.0635062441938,
            281.34180448655121
          ],
          [
            1657.6689927182153,
            300.39451131789212
          ]
        ],
        [
          [
            1645.4667790789244,
            671.30760485185237
          ],
          [
            1514.9816010988641,
            695.13391727063311
          ],
          [
            1217.2395519405493,
            540.36424953844585
          ],
          [
            -1,
            -1
          ],
          [
            1466.6061603341636,
            282.17573907160272
          ],
          [
            1652.4585796042725,
            302.17362501271208
          ]
        ],
        [
          [
            1653.0003873723315,
            671.96674759003793
          ],
          [
            1515.6637021434753,
            693.75018557926512
          ],
          [
            1216.9226217158152,
            542.26473939803725
          ],
          [
            -1,
            -1
          ],
          [
            1465.4366831367342,
            283.1129658281609
          ],
          [
            1646.2161592742036,
            305.40626599110584
          ]
        ],
        [
          [
            1660.5425966948792,
            673.06574275731907
          ],
          [
            1516.1658422884395,
            692.42487700934839
          ],
          [
            1216.9180370462332,
            543.91836468284407
          ],
          [
            -1,
            -1
          ],
          [
            1464.1649427069231,
            283.85627825884552
          ],
          [
            1641.3834164424343,
            308.04861898175557
          ]
        ],
        [
          [
            1667.7793716650572,
            674.86116382657463
          ],
          [
            1516.7684618249461,
            690.60752893838117
          ],
          [
            1217.0108979109777,
            545.32564974799027
          ],
          [
            -1,
            -1
          ],
          [
            1462.5179584685773,
            284.74085440815014
          ],
          [
            1634.6265929154188,
            311.739617525151
          ]
        ],
        [
          [
            1673.4603738560315,
            675.62298537829679
          ],
          [
            1517.470572663527,
            688.83594092396208
          ],
          [
            1217.2134159567449,
            546.7239061405952
          ],
          [
            -1,
            -1
          ],
          [
            1460.9511125973472,
            285.69814525997322
          ],
          [
            1629.6609384259157,
            315.63100013134141
          ]
        ],
        [
          [
            1677.4996989200829,
            675.75926392036888
          ],
          [
            1518.149529415957,
            687.56771708675831
          ],
          [
            1217.1724287811919,
            548.33892093713928
          ],
          [
            -1,
            -1
          ],
          [
            1459.9010137736343,
            286.41272818688788
          ],
          [
            1623.4838729390553,
            320.19202671476
          ]
        ],
        [
          [
            1681.627612949377,
            673.22360543702541
          ],
          [
            1519.0322262872778,
            686.36770558146861
          ],
          [
            1217.3840462601017,
            549.89244608552008
          ],
          [
            -1,
            -1
          ],
          [
            1458.6019172365475,
            287.52641900865206
          ],
          [
            1621.9218008811786,
            321.31350249783281
          ]
        ],
        [
          [
            1682.8866958138447,
            667.00025802246239
          ],
          [
            1519.8945099145351,
            684.788987764621
          ],
          [
            1217.694424582482,
            551.270329472799
          ],
          [
            -1,
            -1
          ],
          [
            1457.8517459385619,
            288.46247711343682
          ],
          [
            1620.7367009865823,
            322.50378254550043
          ]
        ],
        [
          [
            1679.7702131269657,
            656.71466648104536
          ],
          [
            1520.441675109555,
            683.4682095244217
          ],
          [
            1217.8608346534716,
            552.68794415612876
          ],
          [
            -1,
            -1
          ],
          [
            1457.2299942787288,
            289.84094452077761
          ],
          [
            1619.8202797790148,
            323.79721576710506
          ]
        ],
        [
          [
            1676.9856178099653,
            649.72611891668134
          ],
          [
            1521.1901796617828,
            681.69500235517512
          ],
          [
            1217.8098995331118,
            554.4582641074021
          ],
          [
            -1,
            -1
          ],
          [
            1457.089769004486,
            291.35672455679526
          ],
          [
            1619.1207271722856,
            325.25629852608245
          ]
        ],
        [
          [
            1675.099126600478,
            642.64606699614683
          ],
          [
            1521.8423397209197,
            680.44972664332647
          ],
          [
            1217.8402233270472,
            555.8450326045886
          ],
          [
            -1,
            -1
          ],
          [
            1457.877568005671,
            292.82433527427787
          ],
          [
            1618.337239919156,
            327.00853557867691
          ]
        ],
        [
          [
            1672.5377521446414,
            636.95181057380546
          ],
          [
            1522.6800089020962,
            679.253450259963
          ],
          [
            1217.6014566327722,
            557.5148235824056
          ],
          [
            -1,
            -1
          ],
          [
            1459.7233590494327,
            294.01136415121618
          ],
          [
            1617.6073763352122,
            328.78238571730259
          ]
        ],
        [
          [
            1670.861357605135,
            631.3160443530063
          ],
          [
            1523.9010942270054,
            677.91580176096636
          ],
          [
            1217.5798723693583,
            558.9739540973344
          ],
          [
            -1,
            -1
          ],
          [
            1462.4422633501847,
            294.42374674463207
          ],
          [
            1616.9941885277824,
            330.03370602316471
          ]
        ],
        [
          [
            1669.9804289393312,
            625.44664060436264
          ],
          [
            1524.8147754302433,
            676.50717643308349
          ],
          [
            1217.3174335492211,
            560.4859315050403
          ],
          [
            -1,
            -1
          ],
          [
            1465.1070418147426,
            293.7444414120838
          ],
          [
            1616.4683185924323,
            331.31299612775592
          ]
        ],
        [
          [
            1670.0143789650213,
            618.49225336284
          ],
          [
            1525.4623992229103,
            675.00899305531584
          ],
          [
            1216.7943435435122,
            561.97889846742612
          ],
          [
            -1,
            -1
          ],
          [
            -1,
            -1
          ],
          [
            1616.0202090305518,
            332.61613675226909
          ]
        ],
        [
          [
            1669.4931197885062,
            610.94186161459959
          ],
          [
            1526.3741587933932,
            673.39675650320055
          ],
          [
            1216.3846386072967,
            563.29723166101826
          ],
          [
            -1,
            -1
          ],
          [
            -1,
            -1
          ],
          [
            1615.3409113887833,
            334.39497806403449
          ]
        ],
        [
          [
            1668.0723572472668,
            603.83204914664532
          ],
          [
            1526.9340088113211,
            671.85135911738553
          ],
          [
            1216.0815585364569,
            564.67107811495475
          ],
          [
            -1,
            -1
          ],
          [
            -1,
            -1
          ],
          [
            1614.6094749152053,
            335.73826741927672
          ]
        ],
        [
          [
            1666.0737574641769,
            598.20422320247872
          ],
          [
            1527.4001325192144,
            670.04232144150262
          ],
          [
            1215.4965794855382,
            566.130839285239
          ],
          [
            -1,
            -1
          ],
          [
            -1,
            -1
          ],
          [
            1613.6023131418854,
            337.16459350383462
          ]
        ],
        [
          [
            1664.6759875862804,
            592.72841153807644
          ],
          [
            1527.563778337387,
            668.32584448017724
          ],
          [
            1214.6390015046725,
            567.53519602899894
          ],
          [
            -1,
            -1
          ],
          [
            -1,
            -1
          ],
          [
            1612.4497559484576,
            338.51799814477386
          ]
        ],
        [
          [
            1662.4440307184548,
            585.4116747320918
          ],
          [
            1527.5369059240525,
            666.478488489461
          ],
          [
            1213.9199582474084,
            568.70727499581312
          ],
          [
            -1,
            -1
          ],
          [
            -1,
            -1
          ],
          [
            1611.4338662443927,
            340.07948629635962
          ]
        ],
        [
          [
            1661.3919295801077,
            579.76806339867233
          ],
          [
            1527.5050713151313,
            664.55381461705952
          ],
          [
            1212.8700151488633,
            570.31526233190709
          ],
          [
            -1,
            -1
          ],
          [
            -1,
            -1
          ],
          [
            1610.8790911900232,
            341.34842884029672
          ]
        ],
        [
          [
            1660.6018453422269,
            572.26339030338113
          ],
          [
            1527.2256293384726,
            663.01381253315617
          ],
          [
            1211.7226529437271,
            571.82125031254338
          ],
          [
            -1,
            -1
          ],
          [
            -1,
            -1
          ],
          [
            1610.268091824782,
            342.68672260770984
          ]
        ],
        [
          [
            1658.8445049904433,
            565.96896771950037
          ],
          [
            1526.6562775486038,
            661.40177905489838
          ],
          [
            1210.4693869775138,
            573.02671486649626
          ],
          [
            -1,
            -1
          ],
          [
            -1,
            -1
          ],
          [
            1610.041021401011,
            344.24134945445587
          ]
        ],
        [
          [
            1655.98410224243,
            559.43888068022852
          ],
          [
            1526.1968398315169,
            659.58616535049589
          ],
          [
            1209.2238359436028,
            573.9013858867811
          ],
          [
            -1,
            -1
          ],
          [
            -1,
            -1
          ],
          [
            1610.2990906606767,
            345.99231315770163
          ]
        ],
        [
          [
            1655.3484568613273,
            557.654131059671
          ],
          [
            1526.0587249870755,
            657.91939322733572
          ],
          [
            1207.620061934243,
            574.74292950795711
          ],
          [
            -1,
            -1
          ],
          [
            -1,
            -1
          ],
          [
            1610.5526040348552,
            347.96794438283365
          ]
        ],
        [
          [
            1655.0681747128785,
            556.13228489163714
          ],
          [
            1526.102191374446,
            656.48320988243563
          ],
          [
            1206.313375741538,
            575.282023249928
          ],
          [
            -1,
            -1
          ],
          [
            -1,
            -1
          ],
          [
            1610.7993063404826,
            349.81217333904664
          ]
        ],
        [
          [
            1654.9245999817572,
            554.73722050671392
          ],
          [
            1525.906367169755,
            654.71055927743816
          ],
          [
            1204.5929588198042,
            576.1050875334812
          ],
          [
            -1,
            -1
          ],
          [
            -1,
            -1
          ],
          [
            1611.3140759984478,
            351.56796696406286
          ]
        ],
        [
          [
            1655.0264629777053,
            553.04732669860653
          ],
          [
            1525.485471019897,
            652.93581875157554
          ],
          [
            1203.3605570398258,
            576.91752513671281
          ],
          [
            -1,
            -1
          ],
          [
            -1,
            -1
          ],
          [
            1612.2378102405705,
            353.89554305352306
          ]
        ],
        [
          [
            1654.9557054460474,
            551.61707242717807
          ],
          [
            1525.0940693899331,
            651.60518744513877
          ],
          [
            1202.1210253128131,
            578.06350965236959
          ],
          [
            -1,
            -1
          ],
          [
            -1,
            -1
          ],
          [
            1613.4091834879237,
            356.20355788544191
          ]
        ],
        [
          [
            1654.6983834122618,
            550.18139598125708
          ],
          [
            1524.3625976037224,
            650.09265430385312
          ],
          [
            1200.6352608273507,
            579.20437912287866
          ],
          [
            -1,
            -1
          ],
          [
            -1,
            -1
          ],
          [
            1614.237865147496,
            358.33299205350187
          ]
        ],
        [
          [
            1654.2733034424652,
            548.79868598725
          ],
          [
            1523.5125882666507,
            648.84873871805473
          ],
          [
            1199.5705777086387,
            580.33610515074167
          ],
          [
            -1,
            -1
          ],
          [
            -1,
            -1
          ],
          [
            1615.3004375841097,
            360.86941469512703
          ]
        ],
        [
          [
            1653.621768287114,
            547.44192683310712
          ],
          [
            1522.4030581340849,
            647.27738223160623
          ],
          [
            1198.5884598198024,
            581.30640774812753
          ],
          [
            -1,
            -1
          ],
          [
            -1,
            -1
          ],
          [
            1616.1539209937375,
            363.30905211800842
          ]
        ],
        [
          [
            1653.1442583188621,
            546.09804345298
          ],
          [
            1521.2251382892591,
            645.77317984645492
          ],
          [
            1197.1437727390662,
            582.51324096092719
          ],
          [
            -1,
            -1
          ],
          [
            -1,
            -1
          ],
          [
            1616.8271094851352,
            365.975382415449
          ]
        ],
        [
          [
            1652.404828392255,
            544.74824112379429
          ],
          [
            1520.4824505641232,
            644.45997893616459
          ],
          [
            1195.6925980670403,
            583.36747272169316
          ],
          [
            -1,
            -1
          ],
          [
            -1,
            -1
          ],
          [
            1616.9817256081674,
            368.72103240306552
          ]
        ],
        [
          [
            1651.6755111874872,
            543.574473581457
          ],
          [
            1519.6230721942204,
            643.29482074328291
          ],
          [
            1194.3137638065243,
            583.93289134080874
          ],
          [
            -1,
            -1
          ],
          [
            -1,
            -1
          ],
          [
            1616.920105645894,
            371.47034194916057
          ]
        ],
        [
          [
            1651.0177555157043,
            542.00617392625475
          ],
          [
            1518.3770734425966,
            642.0347528039913
          ],
          [
            1193.0321306193493,
            584.68382500540247
          ],
          [
            -1,
            -1
          ],
          [
            -1,
            -1
          ],
          [
            1616.3371448928015,
            374.15784204411017
          ]
        ],
        [
          [
            1650.6533055354664,
            540.53080006823848
          ],
          [
            1517.4794795954904,
            640.94321635758467
          ],
          [
            1191.6597998782183,
            585.2477850181491
          ],
          [
            -1,
            -1
          ],
          [
            -1,
            -1
          ],
          [
            1615.5170754438468,
            376.78272034583983
          ]
        ],
        [
          [
            1650.5250918132861,
            538.87885584186063
          ],
          [
            1516.6029366293535,
            639.88395356463684
          ],
          [
            1189.9532138289896,
            586.08249336693393
          ],
          [
            -1,
            -1
          ],
          [
            -1,
            -1
          ],
          [
            -1,
            -1
          ]
        ]
      ]
    },
    "eye_pos": [
      {
        "eyeX": 1310.4000244140625,
        "eyeY": 313.10000610351562,
        "pupSize": 1921
      },
      {
        "eyeX": 1310.300048828125,
        "eyeY": 312.20001220703125,
        "pupSize": 1916
      },
      {
        "eyeX": 1309.5999755859375,
        "eyeY": 312.5,
        "pupSize": 1922
      },
      {
        "eyeX": 1310.199951171875,
        "eyeY": 312.89999389648438,
        "pupSize": 1918
      },
      {
        "eyeX": 1310.800048828125,
        "eyeY": 311,
        "pupSize": 1920
      },
      {
        "eyeX": 1311.300048828125,
        "eyeY": 310.89999389648438,
        "pupSize": 1919
      },
      {
        "eyeX": 1311.0999755859375,
        "eyeY": 312,
        "pupSize": 1919
      },
      {
        "eyeX": 1312.300048828125,
        "eyeY": 311.29998779296875,
        "pupSize": 1925
      },
      {
        "eyeX": 1312.800048828125,
        "eyeY": 311.5,
        "pupSize": 1929
      },
      {
        "eyeX": 1314.5,
        "eyeY": 311.10000610351562,
        "pupSize": 1939
      },
      {
        "eyeX": 1315,
        "eyeY": 309.39999389648438,
        "pupSize": 1944
      },
      {
        "eyeX": 1317.5999755859375,
        "eyeY": 310.60000610351562,
        "pupSize": 1947
      },
      {
        "eyeX": 1319.199951171875,
        "eyeY": 310.20001220703125,
        "pupSize": 1951
      },
      {
        "eyeX": 1320.4000244140625,
        "eyeY": 311.10000610351562,
        "pupSize": 1959
      },
      {
        "eyeX": 1321.699951171875,
        "eyeY": 311.70001220703125,
        "pupSize": 1965
      },
      {
        "eyeX": 1322.5999755859375,
        "eyeY": 311.10000610351562,
        "pupSize": 1976
      },
      {
        "eyeX": 1323,
        "eyeY": 310.60000610351562,
        "pupSize": 1988
      },
      {
        "eyeX": 1323.0999755859375,
        "eyeY": 308.39999389648438,
        "pupSize": 2002
      },
      {
        "eyeX": 1323.5999755859375,
        "eyeY": 309,
        "pupSize": 2007
      },
      {
        "eyeX": 1323.800048828125,
        "eyeY": 308.60000610351562,
        "pupSize": 2017
      },
      {
        "eyeX": 1324.0999755859375,
        "eyeY": 310,
        "pupSize": 2025
      },
      {
        "eyeX": 1324.9000244140625,
        "eyeY": 308.20001220703125,
        "pupSize": 2041
      },
      {
        "eyeX": 1323.800048828125,
        "eyeY": 308.70001220703125,
        "pupSize": 2052
      },
      {
        "eyeX": 1398,
        "eyeY": 301.10000610351562,
        "pupSize": 2034
      },
      {
        "eyeX": 1460.9000244140625,
        "eyeY": 293.60000610351562,
        "pupSize": 2004
      },
      {
        "eyeX": 1459.300048828125,
        "eyeY": 293.89999389648438,
        "pupSize": 2015
      },
      {
        "eyeX": 1460.5999755859375,
        "eyeY": 295.70001220703125,
        "pupSize": 2024
      },
      {
        "eyeX": 1460,
        "eyeY": 295.39999389648438,
        "pupSize": 2032
      },
      {
        "eyeX": 1458.9000244140625,
        "eyeY": 295.5,
        "pupSize": 2042
      },
      {
        "eyeX": 1457.800048828125,
        "eyeY": 294.39999389648438,
        "pupSize": 2062
      },
      {
        "eyeX": 1456.4000244140625,
        "eyeY": 294,
        "pupSize": 2065
      },
      {
        "eyeX": 1456,
        "eyeY": 296.29998779296875,
        "pupSize": 2078
      },
      {
        "eyeX": 1454.699951171875,
        "eyeY": 296.79998779296875,
        "pupSize": 2082
      },
      {
        "eyeX": 1454.0999755859375,
        "eyeY": 296.70001220703125,
        "pupSize": 2095
      },
      {
        "eyeX": 1453.699951171875,
        "eyeY": 296.79998779296875,
        "pupSize": 2104
      },
      {
        "eyeX": 1455.5999755859375,
        "eyeY": 298.29998779296875,
        "pupSize": 2106
      },
      {
        "eyeX": 1457,
        "eyeY": 298,
        "pupSize": 2113
      },
      {
        "eyeX": 1458.4000244140625,
        "eyeY": 298.29998779296875,
        "pupSize": 2123
      },
      {
        "eyeX": 1459.300048828125,
        "eyeY": 297.60000610351562,
        "pupSize": 2128
      },
      {
        "eyeX": 1460.800048828125,
        "eyeY": 298,
        "pupSize": 2133
      },
      {
        "eyeX": 1460.5999755859375,
        "eyeY": 298.10000610351562,
        "pupSize": 2131
      },
      {
        "eyeX": 1462.4000244140625,
        "eyeY": 298.39999389648438,
        "pupSize": 2138
      },
      {
        "eyeX": 1462.0999755859375,
        "eyeY": 298,
        "pupSize": 2149
      },
      {
        "eyeX": 1512.4000244140625,
        "eyeY": 320,
        "pupSize": 2146
      },
      {
        "eyeX": 1582.0999755859375,
        "eyeY": 332.60000610351562,
        "pupSize": 2123
      },
      {
        "eyeX": 1581.5999755859375,
        "eyeY": 338,
        "pupSize": 2121
      },
      {
        "eyeX": 1582.800048828125,
        "eyeY": 335.20001220703125,
        "pupSize": 2131
      },
      {
        "eyeX": 1584,
        "eyeY": 338.60000610351562,
        "pupSize": 2128
      },
      {
        "eyeX": 1582.9000244140625,
        "eyeY": 337.5,
        "pupSize": 2139
      },
      {
        "eyeX": 1582.300048828125,
        "eyeY": 337.89999389648438,
        "pupSize": 2143
      },
      {
        "eyeX": 1581.199951171875,
        "eyeY": 338.29998779296875,
        "pupSize": 2153
      },
      {
        "eyeX": 1581.199951171875,
        "eyeY": 339.20001220703125,
        "pupSize": 2154
      },
      {
        "eyeX": 1582,
        "eyeY": 342.10000610351562,
        "pupSize": 2153
      },
      {
        "eyeX": 1581.800048828125,
        "eyeY": 342.29998779296875,
        "pupSize": 2164
      }
    ],
    "all_joy_vec": [
      [
        0.91399883396970416,
        -0.40571681195388148
      ],
      [
        0.91722199335573729,
        -0.39837647383414582
      ],
      [
        0.91722199335573729,
        -0.39837647383414582
      ],
      [
        0.91441323774223926,
        -0.40478195444183906
      ],
      [
        0.91722199335573729,
        -0.39837647383414582
      ],
      [
        0.91722199335573729,
        -0.39837647383414582
      ],
      [
        0.91722199335573729,
        -0.39837647383414582
      ],
      [
        0.91722199335573729,
        -0.39837647383414582
      ],
      [
        0.91722199335573729,
        -0.39837647383414582
      ],
      [
        0.91722199335573729,
        -0.39837647383414582
      ],
      [
        0.91181476910023229,
        -0.41060178622442706
      ],
      [
        0.91722199335573729,
        -0.39837647383414582
      ],
      [
        0.91441323774223926,
        -0.40478195444183906
      ],
      [
        0.91722199335573729,
        -0.39837647383414582
      ],
      [
        0.91722199335573729,
        -0.39837647383414582
      ],
      [
        0.91722199335573729,
        -0.39837647383414582
      ],
      [
        0.92037032909508076,
        -0.39104789645440208
      ],
      [
        0.92037032909508076,
        -0.39104789645440208
      ],
      [
        0.9151406526281749,
        -0.40313469945823066
      ],
      [
        0.92037032909508076,
        -0.39104789645440208
      ],
      [
        0.92037032909508076,
        -0.39104789645440208
      ],
      [
        0.92037032909508076,
        -0.39104789645440208
      ],
      [
        0.92037032909508076,
        -0.39104789645440208
      ],
      [
        0.92037032909508076,
        -0.39104789645440208
      ],
      [
        0.92037032909508076,
        -0.39104789645440208
      ],
      [
        0.92037032909508076,
        -0.39104789645440208
      ],
      [
        0.92037032909508076,
        -0.39104789645440208
      ],
      [
        0.92469071351352072,
        -0.38071916728982247
      ],
      [
        0.92469071351352072,
        -0.38071916728982247
      ],
      [
        0.92469071351352072,
        -0.38071916728982247
      ],
      [
        0.92469071351352072,
        -0.38071916728982247
      ],
      [
        0.92037032909508076,
        -0.39104789645440208
      ],
      [
        0.9151406526281749,
        -0.40313469945823066
      ],
      [
        0.92252791912415411,
        -0.38593035438594131
      ],
      [
        0.92150666225214029,
        -0.38836255152231131
      ],
      [
        0.92469071351352072,
        -0.38071916728982247
      ],
      [
        0.92469071351352072,
        -0.38071916728982247
      ],
      [
        0.92469071351352072,
        -0.38071916728982247
      ],
      [
        0.934546238877209,
        -0.35584171677933252
      ],
      [
        0.96700134135841487,
        -0.25477128137022487
      ],
      [
        0.988015073791109,
        -0.15435742276142569
      ],
      [
        0.99937022975368883,
        -0.035484417454133561
      ],
      [
        0.99994665762065027,
        -0.01032869368749542
      ],
      [
        0.9999647847373192,
        0.008392215753121466
      ],
      [
        0.9845218035609804,
        0.17526214169932489
      ],
      [
        0.94161150039798536,
        0.33670132509132583
      ],
      [
        0.89380519892595,
        0.44845542294964269
      ],
      [
        0.85100694705115676,
        0.52515443068745948
      ],
      [
        0.79109093337293712,
        0.611698565582048
      ],
      [
        0.745998098299113,
        0.66594807405240453
      ],
      [
        0.63240155425048272,
        0.77464073878254924
      ],
      [
        0.57362643523874413,
        0.81911703241679146
      ],
      [
        0.52141148691031236,
        0.85330537401212758
      ],
      [
        0.47794174723219568,
        0.8783915335729483
      ]
    ],
    "phase_end": 567230.0892838,
    "phase_duration": 0.88811669999267906
  },
  "switched": true,
  "score": {
    "phase_start": 567230.0893169,
    "phase_end": 567231.6140399,
    "phase_duration": 1.5247230000095442
  },
  "reward_info": {
    "left_reward_this_trial": 0,
    "right_reward_this_trial": 0.30000000000000004,
    "probability_this_trial": 0.30000000000000004,
    "reward_given": true
  },
  "rand_num_generated": 0.034748695491737536,
  "current_trial_reward": 1,
  "current_trial_expected_reward": 1,
  "cumulative_trial_reward": 94
}